docrunner/__init__.py
docrunner/__main__.py
docrunner/constants/help.py
docrunner/constants/language_abbrev.py
docrunner/constants/language_color.py
docrunner/exceptions/base_exception.py
docrunner/exceptions/error.py
docrunner/exceptions/warning.py
docrunner/languages/dart.py
docrunner/languages/javascript.py
docrunner/languages/python.py
docrunner/languages/typescript.py
docrunner/main.py
docrunner/models/options.py
docrunner/models/snippet.py
docrunner/models/snippet_options.py
docrunner/utils/file.py
docrunner/utils/general.py
docrunner/utils/language.py
docrunner-0.1.8.dist-info/entry_points.txt
docrunner-0.1.8.dist-info/LICENSE
docrunner-0.1.8.dist-info/WHEEL
docrunner-0.1.8.dist-info/METADATA
docrunner-0.1.8.dist-info/RECORD
